fasignalprovider/__init__.py
fasignalprovider/code.py
fasignalprovider/direction.py
fasignalprovider/event.py
fasignalprovider/order_type.py
fasignalprovider/side.py
fasignalprovider/trading_signal.py
fa_signal_provider-1.1.35.dist-info/LICENSE
fa_signal_provider-1.1.35.dist-info/METADATA
fa_signal_provider-1.1.35.dist-info/WHEEL
fa_signal_provider-1.1.35.dist-info/top_level.txt
fa_signal_provider-1.1.35.dist-info/RECORD
