Metadata-Version: 2.1
Name: fa-signal-provider
Version: 1.1.35
Summary: A model library for all signal providers of Freya Alpha using python. It includes models to handle signal ingestion, signal status reports, profit & performance reports, etc.
Author-email: Brayan Svan <hello@freya-alpha.com>
Project-URL: Homepage, https://github.com/svabra/fa-signal-provider
Keywords: finance,trading,models
Classifier: License :: OSI Approved :: MIT License
Classifier: Programming Language :: Python
Requires-Python: >=3.9
License-File: LICENSE
Requires-Dist: sqlmodel
Requires-Dist: tomli; python_version < "3.11"
Provides-Extra: dev
Requires-Dist: black; extra == "dev"
Requires-Dist: bumpver; extra == "dev"
Requires-Dist: isort; extra == "dev"
Requires-Dist: pip-tools; extra == "dev"
Requires-Dist: pytest; extra == "dev"
